Metadata-Version: 2.4
Name: opentips
Version: 1.5.1
Summary: Automated assistant that provides coding tips as you work
Author: kgilpin@gmail.com
Classifier: Development Status :: 5 - Production/Stable
Classifier: Intended Audience :: Developers
Classifier: License :: OSI Approved :: GNU General Public License v3 (GPLv3)
Classifier: Programming Language :: Python :: 3.11
Requires-Python: >=3.11
License-File: LICENSE.txt
Requires-Dist: aiohttp~=3.11.11
Requires-Dist: jsonrpcserver~=5.0.9
Requires-Dist: litellm~=1.61.9
Requires-Dist: colorama~=0.4.6
Requires-Dist: charset-normalizer~=3.4.1
Requires-Dist: unidiff~=0.7.5
Provides-Extra: dev
Requires-Dist: flake8~=7.1.1; extra == "dev"
Requires-Dist: pytest~=8.3.4; extra == "dev"
Requires-Dist: pytest-asyncio~=0.25.3; extra == "dev"
Requires-Dist: python-semantic-release~=9.21.0; extra == "dev"
Requires-Dist: pytest-cov~=4.1.0; extra == "dev"
Requires-Dist: build~=1.2.2; extra == "dev"
Requires-Dist: twine~=6.1.0; extra == "dev"
Dynamic: author
Dynamic: classifier
Dynamic: license-file
Dynamic: provides-extra
Dynamic: requires-dist
Dynamic: requires-python
Dynamic: summary
